orbit/__init__.py
orbit/orbit.py
orbit_simulation/__init__.py
orbit_simulation/code_simulation.py
orbit_simulation/face_widget.py
orbit_simulation/main_window.py
orbit_simulation/navigator_widgets.py
orbit_simulation/temperature.py
orbit_simulation/test.py
orbit_simulation/workspace_scene.py
orbit_utils/__init__.py
orbit_utils/sound_player.py
orbitpysdk-0.0.0.data/data/share/orbitpysdk/resource/images/faces/background-robot.png
orbitpysdk-0.0.0.data/data/share/orbitpysdk/resource/images/faces/breathe.png
orbitpysdk-0.0.0.data/data/share/orbitpysdk/resource/images/faces/curious.png
orbitpysdk-0.0.0.data/data/share/orbitpysdk/resource/images/faces/default face.png
orbitpysdk-0.0.0.data/data/share/orbitpysdk/resource/images/faces/error.png
orbitpysdk-0.0.0.data/data/share/orbitpysdk/resource/images/faces/heart eyes.png
orbitpysdk-0.0.0.data/data/share/orbitpysdk/resource/images/faces/hello.png
orbitpysdk-0.0.0.data/data/share/orbitpysdk/resource/images/faces/loading.png
orbitpysdk-0.0.0.data/data/share/orbitpysdk/resource/images/faces/orbit.png
orbitpysdk-0.0.0.data/data/share/orbitpysdk/resource/images/faces/orbit_v5.png
orbitpysdk-0.0.0.data/data/share/orbitpysdk/resource/images/faces/playful.png
orbitpysdk-0.0.0.data/data/share/orbitpysdk/resource/images/faces/shy.png
orbitpysdk-0.0.0.data/data/share/orbitpysdk/resource/images/faces/star eyes.png
orbitpysdk-0.0.0.data/data/share/orbitpysdk/resource/images/faces/surprised.png
orbitpysdk-0.0.0.data/data/share/orbitpysdk/resource/images/faces/thank you.png
orbitpysdk-0.0.0.data/data/share/orbitpysdk/resource/images/lips/1_face.png
orbitpysdk-0.0.0.data/data/share/orbitpysdk/resource/images/lips/1_face_.png
orbitpysdk-0.0.0.data/data/share/orbitpysdk/resource/images/lips/2_face.png
orbitpysdk-0.0.0.data/data/share/orbitpysdk/resource/images/lips/3_face.png
orbitpysdk-0.0.0.data/data/share/orbitpysdk/resource/images/lips/4_face.png
orbitpysdk-0.0.0.data/data/share/orbitpysdk/resource/images/lips/5_face.png
orbitpysdk-0.0.0.dist-info/METADATA
orbitpysdk-0.0.0.dist-info/WHEEL
orbitpysdk-0.0.0.dist-info/top_level.txt
orbitpysdk-0.0.0.dist-info/zip-safe
orbitpysdk-0.0.0.dist-info/RECORD
