Metadata-Version: 2.1
Name: orbitpysdk
Version: 0.0.0
Summary: TODO: package description
Home-page: UNKNOWN
Maintainer: Kalebu
Maintainer-email: calebndatimana@gmail.com
License: TODO: License declaration
Platform: UNKNOWN
Requires-Dist: setuptools
Requires-Dist: pyqt5
Requires-Dist: opencv-python
Requires-Dist: pydub
Requires-Dist: sounddevice
